{
  "ato_normativo": {
    "urn_lexml": "br;go;estadual;emenda.constitucional;2019-12-21;65",
    "tipo_ato": "Emenda Constitucional",
    "titulo": "Modifica o sistema de previdência social, estabelece regras de transição e disposições transitórias, e dá outras providências.",
    "ementa": "",
    "entidade_federativa": "Estadual",
    "orgao_publicador": "Assembleia Legislativa do Estado de Goiás",
    "data_publicacao": "21/12/2019",
    "fonte_oficial": "",
    "situacao_vigencia": "vigente"
  },
  "dispositivos": [
    {
      "rotulo": "Art. 1º",
      "tipo_dispositivo": "artigo",
      "caminho_estrutural": "art-1",
      "ordem": 1,
      "versoes": [
        {
          "vigencia_inicio": "21/12/2019",
          "vigencia_fim": null,
          "texto_normalizado": "Art. 1º Fica aberto à SECRETARIA DE ESTADO DA EDUCAÇÃO, 1 (um) crédito suplementar no valor de R$ 51.087.944,16 (cinquenta e um milhões, oitenta e sete mil, novecentos e quarenta e quatro reais e dezesseis centavos), para reforço de dotação consignada no vigente Orçamento-Geral do Estado, conforme quadro 1, que acompanha esta Portaria.",
          "hash_texto": "e37055d9dfd09db65d6d3cf205d40a7c8d996a12891a1ca9124b3bad67798af0",
          "status_vigencia": "vigente",
          "origem_alteracao": null,
          "texto_original_parser": "Art. 1º Fica aberto à SECRETARIA DE ESTADO DA EDUCAÇÃO, 1\n(um) crédito suplementar no valor de R$ 51.087.944,16 (cinquenta\ne um milhões, oitenta e sete mil, novecentos e quarenta e quatro\nreais e dezesseis centavos), para reforço de dotação consignada\nno vigente Orçamento-Geral do Estado, conforme quadro 1, que\nacompanha esta Portaria.",
          "hash_texto_normalizado": "9b2bd3760dfa27eb51c44676170c5ecdc361020a6dcb2ea1ffe9c2820a6f73ce",
          "normalizacao": {
            "regras_aplicadas": [],
            "removido_total_chars": 0
          }
        }
      ],
      "filhos": [
        {
          "rotulo": "Parágrafo único",
          "tipo_dispositivo": "paragrafo",
          "caminho_estrutural": "art-1/par-1",
          "ordem": 1,
          "versoes": [
            {
              "vigencia_inicio": "21/12/2019",
              "vigencia_fim": null,
              "texto_normalizado": "Parágrafo único . Os recursos necessários à execução do disposto neste artigo são os caracterizados no inciso III do §1º do art. 43 da Lei federal nº 4.320, de 17 de março de 1964, provenientes de anulações parciais de dotações orçamentárias, de acordo com o quadro 2 desta portaria.",
              "hash_texto": "29a37bb5ff18a202cc9fa92301e698b04040708e6695057a627ba4170536eb0e",
              "status_vigencia": "vigente",
              "origem_alteracao": null,
              "texto_original_parser": "Parágrafo único . Os recursos necessários à execução do disposto\nneste artigo são os caracterizados no inciso III do §1º do art. 43\nda Lei federal nº 4.320, de 17 de março de 1964, provenientes de\nanulações parciais de dotações orçamentárias, de acordo com o\nquadro 2 desta portaria.",
              "hash_texto_normalizado": "01ffdeb3f2fec06b8d7a8acc9e29c99db4e372f088a6612586ff11edc8e8f70e",
              "normalizacao": {
                "regras_aplicadas": [],
                "removido_total_chars": 0
              }
            }
          ],
          "filhos": [],
          "ancoras": null
        }
      ],
      "ancoras": null
    },
    {
      "rotulo": "Art. 2º",
      "tipo_dispositivo": "artigo",
      "caminho_estrutural": "art-2",
      "ordem": 2,
      "versoes": [
        {
          "vigencia_inicio": "21/12/2019",
          "vigencia_fim": null,
          "texto_normalizado": "Art. 2º Esta Portaria entra em vigor nesta data. GABINETE DA SECRETÁRIA DE ESTADO DA ECONOMIA, em Goiânia, aos 26 dias do mês de Dezembro de 2019. CRISTIANE ALKMIN JUNQUEIRA SCHMIDT QUADRO 1 SUPLEMENTAÇÃO 2400 - SECRETARIA DE ESTADO DA EDUCAÇÃO 2402 - SUBSECRETARIA DE GOVERNANÇA EDUCACIONAL CLASSIF. ORÇAMENTÁRIA DESCRIÇÃO DA AÇÃO GRUPO DE DESPESA FONTE MODALIDADE 12 368 1019",
          "hash_texto": "8b982ebdab22aa62a033fb508e7455dc1ed28e27a261e5cddd4bdb140ec8d8fb",
          "status_vigencia": "vigente",
          "origem_alteracao": null,
          "texto_original_parser": "Art. 2º Esta Portaria entra em vigor nesta data.\nGABINETE DA SECRETÁRIA DE ESTADO DA ECONOMIA, em\nGoiânia, aos 26 dias do mês de Dezembro de 2019.\nCRISTIANE ALKMIN JUNQUEIRA SCHMIDT\nQUADRO 1\nSUPLEMENTAÇÃO\n2400 - SECRETARIA DE ESTADO DA EDUCAÇÃO\n2402 - SUBSECRETARIA DE GOVERNANÇA EDUCACIONAL\nCLASSIF.\nORÇAMENTÁRIA\nDESCRIÇÃO\nDA AÇÃO\nGRUPO DE\nDESPESA\nFONTE\nMODALIDADE\n12 368 1019",
          "hash_texto_normalizado": "5c3bd558677d589711f5ba21640cbaf74d78a099bf3313cdf8437564277dff67",
          "normalizacao": {
            "regras_aplicadas": [],
            "removido_total_chars": 0
          }
        }
      ],
      "filhos": [
        {
          "rotulo": "3",
          "tipo_dispositivo": "item",
          "caminho_estrutural": "art-2/item-1",
          "ordem": 1,
          "versoes": [
            {
              "vigencia_inicio": "21/12/2019",
              "vigencia_fim": null,
              "texto_normalizado": "3. 019 CONSTRUÇÃO, AMPLIAÇÃO, REFORMA E ADEQUAÇÃO DE UNIDADES ESCOLARES E PRÉDIOS PÚBLICOS 4 INVESTIMENTOS 100 90 SALDO CRÉD. SUPLEMENTAR VALOR DA DESPESA VALOR A SUPLEMENTAR R$ 3.285.829,49 R$",
              "hash_texto": "a64e49741096115fe59ac1393073ede6da2a1d504d57476bd836aeaf8c150da7",
              "status_vigencia": "vigente",
              "origem_alteracao": null,
              "texto_original_parser": "3. 019\nCONSTRUÇÃO,\nAMPLIAÇÃO,\nREFORMA E\nADEQUAÇÃO\nDE UNIDADES\nESCOLARES\nE PRÉDIOS\nPÚBLICOS\n4 INVESTIMENTOS\n100\n90\nSALDO CRÉD.\nSUPLEMENTAR\nVALOR DA\nDESPESA\nVALOR A\nSUPLEMENTAR\nR$ 3.285.829,49\nR$",
              "hash_texto_normalizado": "64ecaac7f4f90aedb03e3e904f053d7c52f39b3e60bf52abf2b16568623336dc",
              "normalizacao": {
                "regras_aplicadas": [],
                "removido_total_chars": 0
              }
            }
          ],
          "filhos": [],
          "ancoras": null
        },
        {
          "rotulo": "54",
          "tipo_dispositivo": "item",
          "caminho_estrutural": "art-2/item-2",
          "ordem": 2,
          "versoes": [
            {
              "vigencia_inicio": "21/12/2019",
              "vigencia_fim": null,
              "texto_normalizado": "54. 373.773,65 R$ 51.087.944,16 VALOR TOTAL A SUPLEMENTAR R$ 51.087.944,16 QUADRO 2 REDUÇÃO 1250 - FUNDO ESPECIAL DE COMUNICAÇÃO - FECOM CLASSIF. ORÇAMENTÁRIA DESCRIÇÃO DA AÇÃO GRUPO DE DESPESA FONTE MODALIDADE 04 131 1010",
              "hash_texto": "b9e2345324b2eeeb97f34e35f697bc73776f0cd2abd818a6b4d266acc3344a24",
              "status_vigencia": "vigente",
              "origem_alteracao": null,
              "texto_original_parser": "54. 373.773,65\nR$ 51.087.944,16\nVALOR TOTAL A\nSUPLEMENTAR\nR$ 51.087.944,16\nQUADRO 2\nREDUÇÃO\n1250 - FUNDO ESPECIAL DE COMUNICAÇÃO - FECOM  \nCLASSIF.\nORÇAMENTÁRIA\nDESCRIÇÃO\nDA AÇÃO\nGRUPO DE\nDESPESA\nFONTE\nMODALIDADE\n04 131 1010",
              "hash_texto_normalizado": "a7f16410bcf373fcfd845eddd6adaaceb74fd6dad975cbe258141dd0c6aefd8c",
              "normalizacao": {
                "regras_aplicadas": [],
                "removido_total_chars": 0
              }
            }
          ],
          "filhos": [],
          "ancoras": null
        },
        {
          "rotulo": "2",
          "tipo_dispositivo": "item",
          "caminho_estrutural": "art-2/item-3",
          "ordem": 3,
          "versoes": [
            {
              "vigencia_inicio": "21/12/2019",
              "vigencia_fim": null,
              "texto_normalizado": "2. 038 DIVULGAÇÃO E VEICULAÇÃO DAS AÇÕES GOVERNAMENTAIS 3 - OUTRAS DESPESAS CORRENTES 100 90 SALDO A PROGRAMAR VALOR BLOQUEADO VALOR A REDUZIR R$ 0,00 R$",
              "hash_texto": "89ed01689a92937610f47f420499e483ce3e0d5ea07f3308639c5ff002e127af",
              "status_vigencia": "vigente",
              "origem_alteracao": null,
              "texto_original_parser": "2. 038\nDIVULGAÇÃO\nE VEICULAÇÃO\nDAS AÇÕES\nGOVERNAMENTAIS\n3 - OUTRAS\nDESPESAS\nCORRENTES\n100\n90\nSALDO A PROGRAMAR\nVALOR\nBLOQUEADO\nVALOR A REDUZIR\nR$ 0,00\nR$",
              "hash_texto_normalizado": "edfb2edb1720db2ef2bb91e3c9c68bbe55f789e2c31e7f75e6a698c783d88e95",
              "normalizacao": {
                "regras_aplicadas": [],
                "removido_total_chars": 0
              }
            }
          ],
          "filhos": [],
          "ancoras": null
        },
        {
          "rotulo": "51",
          "tipo_dispositivo": "item",
          "caminho_estrutural": "art-2/item-4",
          "ordem": 4,
          "versoes": [
            {
              "vigencia_inicio": "21/12/2019",
              "vigencia_fim": null,
              "texto_normalizado": "51. 087.944,16 R$ 51.087.944,16 VALOR TOTAL A REDUZIR R$ 51.087.944,16 <#ABC#163442#1#194579/> Protocolo 163442 <#ABC#163444#1#194581> Portaria Orçamentária nº 318/2019 - Economia A SECRETÁRIA DE ESTADO DA ECONOMIA, no uso de suas atribuições legais, com fundamento no art. 1º do Decreto nº 9.453 de 14 de junho de 2019 e no art. 35 do Decreto nº 9.418 de 22 de março de 2019, e considerando o disposto no art. 9º da Lei nº",
              "hash_texto": "97cd2b81bfc6df8344209199a61d24f1c62db38cd765a5fca2c64a201c845f5c",
              "status_vigencia": "vigente",
              "origem_alteracao": null,
              "texto_original_parser": "51. 087.944,16\nR$ 51.087.944,16\nVALOR TOTAL A\nREDUZIR\nR$ 51.087.944,16\n<#ABC#163442#1#194579/>\nProtocolo 163442\n<#ABC#163444#1#194581>\nPortaria Orçamentária nº 318/2019 - Economia\nA\nSECRETÁRIA\nDE\nESTADO\nDA\nECONOMIA, no uso de suas atribuições\nlegais, com fundamento no art. 1º do Decreto\nnº 9.453 de 14 de junho de 2019 e no art. 35\ndo Decreto nº 9.418 de 22 de março de 2019,\ne considerando o disposto no art. 9º da Lei nº",
              "hash_texto_normalizado": "4754b6f88f12c002a97252b26f8bd408fc708d28a5f066c8d02ac59f87b27f5b",
              "normalizacao": {
                "regras_aplicadas": [],
                "removido_total_chars": 0
              }
            }
          ],
          "filhos": [],
          "ancoras": null
        },
        {
          "rotulo": "20",
          "tipo_dispositivo": "item",
          "caminho_estrutural": "art-2/item-5",
          "ordem": 5,
          "versoes": [
            {
              "vigencia_inicio": "21/12/2019",
              "vigencia_fim": null,
              "texto_normalizado": "20. 419, de 18 de fevereiro de 2019, RESOLVE:",
              "hash_texto": "705be8e3fcfa1f620f946804028ad44be8b6bc76b976501abaef9adf4513967e",
              "status_vigencia": "vigente",
              "origem_alteracao": null,
              "texto_original_parser": "20. 419, de 18 de fevereiro de 2019,\nRESOLVE:",
              "hash_texto_normalizado": "62b9eb5aae76f46a61d3329db64bd9557c759e6468d7a0fc5f7d36e12e2beea1",
              "normalizacao": {
                "regras_aplicadas": [],
                "removido_total_chars": 0
              }
            }
          ],
          "filhos": [],
          "ancoras": null
        }
      ],
      "ancoras": null
    },
    {
      "rotulo": "Art. 1º",
      "tipo_dispositivo": "artigo",
      "caminho_estrutural": "art-3",
      "ordem": 3,
      "versoes": [
        {
          "vigencia_inicio": "21/12/2019",
          "vigencia_fim": null,
          "texto_normalizado": "Art. 1º Fica aberto à SECRETARIA DE ESTADO DA EDUCAÇÃO, 1 (um) crédito suplementar no valor de R$ 6.272.065,89 (seis milhões, duzentos e setenta e dois mil e sessenta e cinco reais e oitenta e nove centavos), para reforço de dotação consignada no vigente Orçamento-Geral do Estado, conforme quadro 1, que acompanha esta Portaria.",
          "hash_texto": "67bb9ad35c8b8bab643839e57f4a7348105cc72e9f44b77c3f44c97aa6069fa8",
          "status_vigencia": "vigente",
          "origem_alteracao": null,
          "texto_original_parser": "Art. 1º Fica aberto à SECRETARIA DE ESTADO DA EDUCAÇÃO, 1\n(um) crédito suplementar no valor de R$ 6.272.065,89 (seis milhões,\nduzentos e setenta e dois mil e sessenta e cinco reais e oitenta e\nnove centavos), para reforço de dotação consignada no vigente\nOrçamento-Geral do Estado, conforme quadro 1, que acompanha\nesta Portaria.",
          "hash_texto_normalizado": "c8662e0473093a2da3a3b5f146f89ef98968cc36f3c8f35b1de28c1c038205d3",
          "normalizacao": {
            "regras_aplicadas": [],
            "removido_total_chars": 0
          }
        }
      ],
      "filhos": [
        {
          "rotulo": "Parágrafo único",
          "tipo_dispositivo": "paragrafo",
          "caminho_estrutural": "art-3/par-1",
          "ordem": 1,
          "versoes": [
            {
              "vigencia_inicio": "21/12/2019",
              "vigencia_fim": null,
              "texto_normalizado": "Parágrafo único . Os recursos necessários à execução do disposto neste artigo são os caracterizados no inciso III do §1º do art. 43 da Lei federal nº 4.320, de 17 de março de 1964, provenientes de anulações parciais de dotações orçamentárias, de acordo com o quadro 2 desta portaria.",
              "hash_texto": "29a37bb5ff18a202cc9fa92301e698b04040708e6695057a627ba4170536eb0e",
              "status_vigencia": "vigente",
              "origem_alteracao": null,
              "texto_original_parser": "Parágrafo único . Os recursos necessários à execução do disposto\nneste artigo são os caracterizados no inciso III do §1º do art. 43\nda Lei federal nº 4.320, de 17 de março de 1964, provenientes de\nanulações parciais de dotações orçamentárias, de acordo com o\nquadro 2 desta portaria.",
              "hash_texto_normalizado": "01ffdeb3f2fec06b8d7a8acc9e29c99db4e372f088a6612586ff11edc8e8f70e",
              "normalizacao": {
                "regras_aplicadas": [],
                "removido_total_chars": 0
              }
            }
          ],
          "filhos": [],
          "ancoras": null
        }
      ],
      "ancoras": null
    },
    {
      "rotulo": "Art. 2º",
      "tipo_dispositivo": "artigo",
      "caminho_estrutural": "art-4",
      "ordem": 4,
      "versoes": [
        {
          "vigencia_inicio": "21/12/2019",
          "vigencia_fim": null,
          "texto_normalizado": "Art. 2º Esta Portaria entra em vigor nesta data. GABINETE DA SECRETÁRIA DE ESTADO DA ECONOMIA, em Goiânia, aos 26 dias do mês de Dezembro de 2019. CRISTIANE ALKMIN JUNQUEIRA SCHMIDT DIARIO OFICIAL DO ESTADO DE GOIAS Assinado digitalmente pela ABC - AGENCIA BRASIL CENTRAL CODIGO DE AUTENTICACAO: 21301716 2 GOIÂNIA, SEGUNDA-FEIRA, 30 DE DEZEMBRO DE 2019 ANO 183 - DIÁRIO OFICIAL/GO N° 23.207 SUPLEMENTO EXTRA Diário Oficial Diretoria Estado de Goiás Imprensa Oficial do Estado de Goiás José Roberto Borges da Rocha Leão Presidente Clebiana Pimenta Gouvêa Cruz Diretora de Gestão Integrada Elizeth Castro de Araújo Diretora de Telerradiodifusão, Imprensa Oficial e Site Previsto Custódio dos Santos Gerente de Imprensa Oficial e Mídias Digitais Rua SC-1, nº 299 - Parque Santa Cruz CEP: 74.860-270 - Goiânia - Goiás Fones: 3201-7639 / 3201-7623 / 3201-7663 www.abc.go.gov.br QUADRO 1 SUPLEMENTAÇÃO 2400 - SECRETARIA DE ESTADO DA EDUCAÇÃO 2402 - SUBSECRETARIA DE GOVERNANÇA EDUCACIONAL CLASSIF. ORÇAMENTÁRIA DESCRIÇÃO DA AÇÃO GRUPO DE DESPESA FONTE MODALIDADE 12 368 1019",
          "hash_texto": "dcbe92ebccd5c990c6189cb26910fb8d8f97e1b12aca8b6dc9db563d5d685a43",
          "status_vigencia": "vigente",
          "origem_alteracao": null,
          "texto_original_parser": "Art. 2º Esta Portaria entra em vigor nesta data.\nGABINETE DA SECRETÁRIA DE ESTADO DA ECONOMIA, em\nGoiânia, aos 26 dias do mês de Dezembro de 2019.\nCRISTIANE ALKMIN JUNQUEIRA SCHMIDT\nDIARIO OFICIAL DO ESTADO DE GOIAS\nAssinado digitalmente pela ABC - AGENCIA BRASIL CENTRAL\nCODIGO DE AUTENTICACAO: 21301716\n2\nGOIÂNIA, SEGUNDA-FEIRA, 30 DE DEZEMBRO DE 2019\nANO 183 - DIÁRIO OFICIAL/GO N° 23.207\nSUPLEMENTO EXTRA\nDiário Oficial\nDiretoria\nEstado de Goiás\nImprensa Oficial do Estado de\nGoiás\nJosé Roberto Borges da Rocha Leão\nPresidente\nClebiana Pimenta Gouvêa Cruz\nDiretora de Gestão Integrada\nElizeth Castro de Araújo\nDiretora de Telerradiodifusão, Imprensa Oficial e Site\nPrevisto Custódio dos Santos\nGerente de Imprensa Oficial e Mídias Digitais\nRua SC-1, nº 299 - Parque Santa Cruz\nCEP: 74.860-270 - Goiânia - Goiás\nFones: 3201-7639 / 3201-7623 / 3201-7663\nwww.abc.go.gov.br\nQUADRO 1\nSUPLEMENTAÇÃO\n2400 - SECRETARIA DE ESTADO DA EDUCAÇÃO\n2402 - SUBSECRETARIA DE GOVERNANÇA EDUCACIONAL\nCLASSIF.\nORÇAMENTÁRIA\nDESCRIÇÃO\nDA AÇÃO\nGRUPO DE\nDESPESA\nFONTE\nMODALIDADE\n12 368 1019",
          "hash_texto_normalizado": "b377e2e60f8b97ae4ec3604a651adb03ddcd608273f12dba37cdb0636d926e85",
          "normalizacao": {
            "regras_aplicadas": [],
            "removido_total_chars": 0
          }
        }
      ],
      "filhos": [
        {
          "rotulo": "3",
          "tipo_dispositivo": "item",
          "caminho_estrutural": "art-4/item-1",
          "ordem": 1,
          "versoes": [
            {
              "vigencia_inicio": "21/12/2019",
              "vigencia_fim": null,
              "texto_normalizado": "3. 019 CONSTRUÇÃO, AMPLIAÇÃO, REFORMA E ADEQUAÇÃO DE UNIDADES ESCOLARES E PRÉDIOS PÚBLICOS 3 - OUTRAS DESPESAS CORRENTES 100 90 SALDO CRÉD. SUPLEMENTAR VALOR DA DESPESA VALOR A SUPLEMENTAR R$ 30.353,09 R$",
              "hash_texto": "369e40a8018e98d0850fb1f29e708e606dbdaea79d20100529bdd8e3eed5a066",
              "status_vigencia": "vigente",
              "origem_alteracao": null,
              "texto_original_parser": "3. 019\nCONSTRUÇÃO,\nAMPLIAÇÃO,\nREFORMA E\nADEQUAÇÃO\nDE UNIDADES\nESCOLARES\nE PRÉDIOS\nPÚBLICOS\n3 - OUTRAS\nDESPESAS\nCORRENTES\n100\n90\nSALDO CRÉD.\nSUPLEMENTAR\nVALOR DA\nDESPESA\nVALOR A\nSUPLEMENTAR\nR$ 30.353,09\nR$",
              "hash_texto_normalizado": "aea60acf9b0ea88223180b9ea6177dc61cf1d6a0c7aeb5f12d253f260fe0e617",
              "normalizacao": {
                "regras_aplicadas": [],
                "removido_total_chars": 0
              }
            }
          ],
          "filhos": [],
          "ancoras": null
        },
        {
          "rotulo": "6",
          "tipo_dispositivo": "item",
          "caminho_estrutural": "art-4/item-2",
          "ordem": 2,
          "versoes": [
            {
              "vigencia_inicio": "21/12/2019",
              "vigencia_fim": null,
              "texto_normalizado": "6. 302.418,98 R$ 6.272.065,89 VALOR TOTAL A SUPLEMENTAR R$ 6.272.065,89 QUADRO 2 REDUÇÃO 1250 - FUNDO ESPECIAL DE COMUNICAÇÃO - FECOM CLASSIF. ORÇAMENTÁRIA DESCRIÇÃO DA AÇÃO GRUPO DE DESPESA FONTE MODALIDADE 04 131 1010",
              "hash_texto": "1eb6e72fa5374806aa043bbb6f6a93bdb126a4ffe0ad38a959d20b110e58883b",
              "status_vigencia": "vigente",
              "origem_alteracao": null,
              "texto_original_parser": "6. 302.418,98\nR$ 6.272.065,89\nVALOR TOTAL A\nSUPLEMENTAR\nR$ 6.272.065,89\nQUADRO 2\nREDUÇÃO\n1250 - FUNDO ESPECIAL DE COMUNICAÇÃO - FECOM  \nCLASSIF.\nORÇAMENTÁRIA\nDESCRIÇÃO\nDA AÇÃO\nGRUPO DE\nDESPESA\nFONTE\nMODALIDADE\n04 131 1010",
              "hash_texto_normalizado": "da98827d27241d6009b11fe63504c7859339dd1b6d1ddfb4e31b747a1f21f041",
              "normalizacao": {
                "regras_aplicadas": [],
                "removido_total_chars": 0
              }
            }
          ],
          "filhos": [],
          "ancoras": null
        },
        {
          "rotulo": "2",
          "tipo_dispositivo": "item",
          "caminho_estrutural": "art-4/item-3",
          "ordem": 3,
          "versoes": [
            {
              "vigencia_inicio": "21/12/2019",
              "vigencia_fim": null,
              "texto_normalizado": "2. 038 DIVULGAÇÃO E VEICULAÇÃO DAS AÇÕES GOVERNAMENTAIS 3 - OUTRAS DESPESAS CORRENTES 100 90 SALDO A PROGRAMAR VALOR BLOQUEADO VALOR A REDUZIR R$ 0,00 R$",
              "hash_texto": "89ed01689a92937610f47f420499e483ce3e0d5ea07f3308639c5ff002e127af",
              "status_vigencia": "vigente",
              "origem_alteracao": null,
              "texto_original_parser": "2. 038\nDIVULGAÇÃO\nE VEICULAÇÃO\nDAS AÇÕES\nGOVERNAMENTAIS\n3 - OUTRAS\nDESPESAS\nCORRENTES\n100\n90\nSALDO A PROGRAMAR\nVALOR\nBLOQUEADO\nVALOR A REDUZIR\nR$ 0,00\nR$",
              "hash_texto_normalizado": "edfb2edb1720db2ef2bb91e3c9c68bbe55f789e2c31e7f75e6a698c783d88e95",
              "normalizacao": {
                "regras_aplicadas": [],
                "removido_total_chars": 0
              }
            }
          ],
          "filhos": [],
          "ancoras": null
        },
        {
          "rotulo": "6",
          "tipo_dispositivo": "item",
          "caminho_estrutural": "art-4/item-4",
          "ordem": 4,
          "versoes": [
            {
              "vigencia_inicio": "21/12/2019",
              "vigencia_fim": null,
              "texto_normalizado": "6. 272.065,89 R$ 6.272.065,89 VALOR TOTAL A REDUZIR R$ 6.272.065,89 <#ABC#163444#2#194581/> Protocolo 163444 <#ABC#163446#2#194583> Portaria Orçamentária nº 319/2019 - Economia A SECRETÁRIA DE ESTADO DA ECONOMIA, no uso de suas atribuições legais, com fundamento no art. 1º do Decreto nº 9.453 de 14 de junho de 2019 e no art. 35 do Decreto nº 9.418 de 22 de março de 2019, e considerando o disposto no art. 9º da Lei nº",
              "hash_texto": "0b7b2f5a7ff948f6ec403ebd8da7a3aa6a9c8f89341bf378cfce594a9c3b96f4",
              "status_vigencia": "vigente",
              "origem_alteracao": null,
              "texto_original_parser": "6. 272.065,89\nR$ 6.272.065,89\nVALOR TOTAL A\nREDUZIR\nR$ 6.272.065,89\n<#ABC#163444#2#194581/>\nProtocolo 163444\n<#ABC#163446#2#194583>\nPortaria Orçamentária nº 319/2019 - Economia\nA\nSECRETÁRIA\nDE\nESTADO\nDA\nECONOMIA, no uso de suas atribuições\nlegais, com fundamento no art. 1º do Decreto\nnº 9.453 de 14 de junho de 2019 e no art. 35\ndo Decreto nº 9.418 de 22 de março de 2019,\ne considerando o disposto no art. 9º da Lei nº",
              "hash_texto_normalizado": "aa6c6971c37038ea5c5e8b2aa2a4e0d017f4f59b64e896f43fcdc6685f1f3e43",
              "normalizacao": {
                "regras_aplicadas": [],
                "removido_total_chars": 0
              }
            }
          ],
          "filhos": [],
          "ancoras": null
        },
        {
          "rotulo": "20",
          "tipo_dispositivo": "item",
          "caminho_estrutural": "art-4/item-5",
          "ordem": 5,
          "versoes": [
            {
              "vigencia_inicio": "21/12/2019",
              "vigencia_fim": null,
              "texto_normalizado": "20. 419, de 18 de fevereiro de 2019, RESOLVE:",
              "hash_texto": "705be8e3fcfa1f620f946804028ad44be8b6bc76b976501abaef9adf4513967e",
              "status_vigencia": "vigente",
              "origem_alteracao": null,
              "texto_original_parser": "20. 419, de 18 de fevereiro de 2019,\nRESOLVE:",
              "hash_texto_normalizado": "62b9eb5aae76f46a61d3329db64bd9557c759e6468d7a0fc5f7d36e12e2beea1",
              "normalizacao": {
                "regras_aplicadas": [],
                "removido_total_chars": 0
              }
            }
          ],
          "filhos": [],
          "ancoras": null
        }
      ],
      "ancoras": null
    },
    {
      "rotulo": "Art. 1º",
      "tipo_dispositivo": "artigo",
      "caminho_estrutural": "art-5",
      "ordem": 5,
      "versoes": [
        {
          "vigencia_inicio": "21/12/2019",
          "vigencia_fim": null,
          "texto_normalizado": "Art. 1º Fica aberto à AGÊNCIA GOIANA DE INFRAESTRUTURA E TRANSPORTES - GOINFRA, 1 (um) crédito suplementar no valor de R$ 600.000,00 (seiscentos mil reais), para reforço de dotação consignada no vigente Orçamento-Geral do Estado, conforme quadro 1, que acompanha esta Portaria.",
          "hash_texto": "ed020b615fc7597268214977bc38ed8df6dd5f2a3ad622d8bb73d866270c2156",
          "status_vigencia": "vigente",
          "origem_alteracao": null,
          "texto_original_parser": "Art. 1º Fica aberto à AGÊNCIA GOIANA DE INFRAESTRUTURA E\nTRANSPORTES - GOINFRA, 1 (um) crédito suplementar no valor\nde R$ 600.000,00 (seiscentos mil reais), para reforço de dotação\nconsignada no vigente Orçamento-Geral do Estado, conforme\nquadro 1, que acompanha esta Portaria.",
          "hash_texto_normalizado": "45d0609c351477177df3ea1e8c6b31138490a0f70c526353fe20fd67520db5b8",
          "normalizacao": {
            "regras_aplicadas": [],
            "removido_total_chars": 0
          }
        }
      ],
      "filhos": [
        {
          "rotulo": "Parágrafo único",
          "tipo_dispositivo": "paragrafo",
          "caminho_estrutural": "art-5/par-1",
          "ordem": 1,
          "versoes": [
            {
              "vigencia_inicio": "21/12/2019",
              "vigencia_fim": null,
              "texto_normalizado": "Parágrafo único . Os recursos necessários à execução do disposto neste artigo são os caracterizados no inciso III do ڇº do art. 43 da Lei federal nº 4.320, de 17 de março de 1964, provenientes de anulações parciais de dotações orçamentárias, de acordo com o quadro 2 desta portaria.",
              "hash_texto": "0cd60f010c27f4de7dd8b20daa62a41531cbc27004c42212d1703b31199b6091",
              "status_vigencia": "vigente",
              "origem_alteracao": null,
              "texto_original_parser": "Parágrafo único . Os recursos necessários à execução do disposto\nneste artigo são os caracterizados no inciso III do ڇº do art. 43 da\nLei federal nº 4.320, de 17 de março de 1964, provenientes de\nanulações parciais de dotações orçamentárias, de acordo com o\nquadro 2 desta portaria.",
              "hash_texto_normalizado": "c914a7cebe02da5c8cbb601c28b07d18abc1cd69514b6e5f7aae439d5cb6bff2",
              "normalizacao": {
                "regras_aplicadas": [],
                "removido_total_chars": 0
              }
            }
          ],
          "filhos": [],
          "ancoras": null
        }
      ],
      "ancoras": null
    },
    {
      "rotulo": "Art. 2º",
      "tipo_dispositivo": "artigo",
      "caminho_estrutural": "art-6",
      "ordem": 6,
      "versoes": [
        {
          "vigencia_inicio": "21/12/2019",
          "vigencia_fim": null,
          "texto_normalizado": "Art. 2º Esta Portaria entra em vigor nesta data. GABINETE DA SECRETÁRIA DE ESTADO DA ECONOMIA, em Goiânia, aos 26 dias do mês de Dezembro de 2019. CRISTIANE ALKMIN JUNQUEIRA SCHMIDT QUADRO 1 SUPLEMENTAÇÃO 2161 - AGÊNCIA GOIANA DE INFRAESTRUTURA E TRANSPORTES - GOINFRA CLASSIF. ORÇAMENTÁRIA DESCRIÇÃO DA AÇÃO GRUPO DE DESPESA FONTE MODALIDADE 26 781 1066",
          "hash_texto": "5d3a94ae6d2947988cd1f0dc30cb4aa31e964b32b9d63aee944e0336b84d62a5",
          "status_vigencia": "vigente",
          "origem_alteracao": null,
          "texto_original_parser": "Art. 2º Esta Portaria entra em vigor nesta data.\nGABINETE DA SECRETÁRIA DE ESTADO DA ECONOMIA, em\nGoiânia, aos 26 dias do mês de Dezembro de 2019.\nCRISTIANE ALKMIN JUNQUEIRA SCHMIDT\nQUADRO 1\nSUPLEMENTAÇÃO\n2161 - AGÊNCIA GOIANA DE INFRAESTRUTURA E\nTRANSPORTES - GOINFRA\nCLASSIF.\nORÇAMENTÁRIA\nDESCRIÇÃO\nDA AÇÃO\nGRUPO DE\nDESPESA\nFONTE\nMODALIDADE\n26 781 1066",
          "hash_texto_normalizado": "95b2198a0ec0a1cc7ef976b192df795f40b6c51098db40f546dfc2b2dd0e18f4",
          "normalizacao": {
            "regras_aplicadas": [],
            "removido_total_chars": 0
          }
        }
      ],
      "filhos": [
        {
          "rotulo": "3",
          "tipo_dispositivo": "item",
          "caminho_estrutural": "art-6/item-1",
          "ordem": 1,
          "versoes": [
            {
              "vigencia_inicio": "21/12/2019",
              "vigencia_fim": null,
              "texto_normalizado": "3. 125 IMPLANTAÇÃO DO AEROPORTO DE CARGAS DE ANÁPOLIS 4 INVESTIMENTOS 100 90 SALDO CRÉD. SUPLEMENTAR VALOR DA DESPESA VALOR A SUPLEMENTAR R$ 10.000,00 R$ 610.000,00 R$ 600.000,00 VALOR TOTAL A SUPLEMENTAR R$ 600.000,00 QUADRO 2 REDUÇÃO 2161 - AGÊNCIA GOIANA DE INFRAESTRUTURA E TRANSPORTES - GOINFRA CLASSIF. ORÇAMENTÁRIA DESCRIÇÃO DA AÇÃO GRUPO DE DESPESA FONTE MODALIDADE 26 782 1068",
              "hash_texto": "f62b55e594f47d9869b96bc39f9abe28f026b602ee01ec253793046061a8c843",
              "status_vigencia": "vigente",
              "origem_alteracao": null,
              "texto_original_parser": "3. 125\nIMPLANTAÇÃO\nDO\nAEROPORTO\nDE CARGAS\nDE ANÁPOLIS\n4 INVESTIMENTOS\n100\n90\nSALDO CRÉD.\nSUPLEMENTAR\nVALOR DA\nDESPESA\nVALOR A\nSUPLEMENTAR\nR$ 10.000,00\nR$ 610.000,00\nR$ 600.000,00\nVALOR TOTAL A\nSUPLEMENTAR\nR$ 600.000,00\nQUADRO 2\nREDUÇÃO\n2161 - AGÊNCIA GOIANA DE INFRAESTRUTURA E\nTRANSPORTES - GOINFRA\nCLASSIF.\nORÇAMENTÁRIA\nDESCRIÇÃO\nDA AÇÃO\nGRUPO DE\nDESPESA\nFONTE\nMODALIDADE\n26 782 1068",
              "hash_texto_normalizado": "d948d67082bda856eec9f855f410c20befbb834b4ec86d0ea32e9be671b21a32",
              "normalizacao": {
                "regras_aplicadas": [],
                "removido_total_chars": 0
              }
            }
          ],
          "filhos": [],
          "ancoras": null
        },
        {
          "rotulo": "2",
          "tipo_dispositivo": "item",
          "caminho_estrutural": "art-6/item-2",
          "ordem": 2,
          "versoes": [
            {
              "vigencia_inicio": "21/12/2019",
              "vigencia_fim": null,
              "texto_normalizado": "2. 356 GMC CONSERVAÇÃO/ MANUTENÇÃO DAS RODOVIAS PAVIMENTADAS E NÃO PAVIMENT., OBRAS DE ARTES ESPEC. E SINALIZAÇÕES 3 - OUTRAS DESPESAS CORRENTES 100 90 SALDO A PROGRAMAR VALOR BLOQUEADO VALOR A REDUZIR R$ 2.343.562,03 R$",
              "hash_texto": "8c17db71880016ac11efa1c72fa027fecf491b4084777551f460dd6e82799cff",
              "status_vigencia": "vigente",
              "origem_alteracao": null,
              "texto_original_parser": "2. 356\nGMC CONSERVAÇÃO/\nMANUTENÇÃO\nDAS RODOVIAS\nPAVIMENTADAS\nE NÃO\nPAVIMENT.,\nOBRAS\nDE ARTES\nESPEC. E\nSINALIZAÇÕES\n3 - OUTRAS\nDESPESAS\nCORRENTES\n100\n90\nSALDO A PROGRAMAR\nVALOR\nBLOQUEADO\nVALOR A REDUZIR\nR$ 2.343.562,03\nR$",
              "hash_texto_normalizado": "14dfc5c643952903227791de8dce312bd39c4499efe6336aabbf786b7fdd3fc1",
              "normalizacao": {
                "regras_aplicadas": [],
                "removido_total_chars": 0
              }
            }
          ],
          "filhos": [],
          "ancoras": null
        },
        {
          "rotulo": "600",
          "tipo_dispositivo": "item",
          "caminho_estrutural": "art-6/item-3",
          "ordem": 3,
          "versoes": [
            {
              "vigencia_inicio": "21/12/2019",
              "vigencia_fim": null,
              "texto_normalizado": "600. 000,00 R$ 600.000,00 VALOR TOTAL A REDUZIR R$ 600.000,00 <#ABC#163446#2#194583/> Protocolo 163446 DIARIO OFICIAL DO ESTADO DE GOIAS Assinado digitalmente pela ABC - AGENCIA BRASIL CENTRAL CODIGO DE AUTENTICACAO: 21301716 3 Diário Oficial GOIÂNIA, SEGUNDA-FEIRA, 30 DE DEZEMBRO DE 2019 ANO 183 - DIÁRIO OFICIAL/GO N° 23.207 SUPLEMENTO EXTRA <#ABC#163447#3#194584> Portaria Orçamentária nº 320/2019 - Economia A SECRETÁRIA DE ESTADO DA ECONOMIA, no uso de suas atribuições legais, com fundamento no art. 1º do Decreto nº 9.453 de 14 de junho de 2019 e no art. 35 do Decreto nº 9.418 de 22 de março de 2019, e considerando o disposto no art. 9º da Lei nº",
              "hash_texto": "38769cafd3b4b791e04dc62f1464ab526890440d4c9b0c87f7b6dcab0f145c93",
              "status_vigencia": "vigente",
              "origem_alteracao": null,
              "texto_original_parser": "600. 000,00\nR$ 600.000,00\nVALOR TOTAL A\nREDUZIR\nR$ 600.000,00\n<#ABC#163446#2#194583/>\nProtocolo 163446\nDIARIO OFICIAL DO ESTADO DE GOIAS\nAssinado digitalmente pela ABC - AGENCIA BRASIL CENTRAL\nCODIGO DE AUTENTICACAO: 21301716\n3\nDiário Oficial\nGOIÂNIA, SEGUNDA-FEIRA, 30 DE DEZEMBRO DE 2019\nANO 183 - DIÁRIO OFICIAL/GO N° 23.207\nSUPLEMENTO EXTRA\n<#ABC#163447#3#194584>\nPortaria Orçamentária nº 320/2019 - Economia\nA\nSECRETÁRIA\nDE\nESTADO\nDA\nECONOMIA, no uso de suas atribuições\nlegais, com fundamento no art. 1º do Decreto\nnº 9.453 de 14 de junho de 2019 e no art. 35\ndo Decreto nº 9.418 de 22 de março de 2019,\ne considerando o disposto no art. 9º da Lei nº",
              "hash_texto_normalizado": "61b61d93f9448c3a911307072b472ee27024e2001633972f31cfea8468f96b3f",
              "normalizacao": {
                "regras_aplicadas": [],
                "removido_total_chars": 0
              }
            }
          ],
          "filhos": [],
          "ancoras": null
        },
        {
          "rotulo": "20",
          "tipo_dispositivo": "item",
          "caminho_estrutural": "art-6/item-4",
          "ordem": 4,
          "versoes": [
            {
              "vigencia_inicio": "21/12/2019",
              "vigencia_fim": null,
              "texto_normalizado": "20. 419, de 18 de fevereiro de 2019, RESOLVE:",
              "hash_texto": "705be8e3fcfa1f620f946804028ad44be8b6bc76b976501abaef9adf4513967e",
              "status_vigencia": "vigente",
              "origem_alteracao": null,
              "texto_original_parser": "20. 419, de 18 de fevereiro de 2019,\nRESOLVE:",
              "hash_texto_normalizado": "62b9eb5aae76f46a61d3329db64bd9557c759e6468d7a0fc5f7d36e12e2beea1",
              "normalizacao": {
                "regras_aplicadas": [],
                "removido_total_chars": 0
              }
            }
          ],
          "filhos": [],
          "ancoras": null
        }
      ],
      "ancoras": null
    },
    {
      "rotulo": "Art. 1º",
      "tipo_dispositivo": "artigo",
      "caminho_estrutural": "art-7",
      "ordem": 7,
      "versoes": [
        {
          "vigencia_inicio": "21/12/2019",
          "vigencia_fim": null,
          "texto_normalizado": "Art. 1º Ficam abertos à AGÊNCIA GOIANA DE INFRAESTRUTURA E TRANSPORTES - GOINFRA, 3 (três) créditos suplementares no valor global de R$ 8.768.225,88 (oito milhões, setecentos e sessenta e oito mil, duzentos e vinte e cinco reais e oitenta e oito centavos), para reforço de dotações consignadas no vigente Orçamento-Geral do Estado, conforme quadro 1, que acompanha esta Portaria.",
          "hash_texto": "6999454cc8c9ff3bba210b5bb2c9cbbf11861fc8499cde0c9dc76ddd12d9be9c",
          "status_vigencia": "vigente",
          "origem_alteracao": null,
          "texto_original_parser": "Art. 1º Ficam abertos à AGÊNCIA GOIANA DE INFRAESTRUTURA\nE TRANSPORTES - GOINFRA, 3 (três) créditos suplementares no\nvalor global de R$ 8.768.225,88 (oito milhões, setecentos e sessenta\ne oito mil, duzentos e vinte e cinco reais e oitenta e oito centavos),\npara reforço de dotações consignadas no vigente Orçamento-Geral\ndo Estado, conforme quadro 1, que acompanha esta Portaria.",
          "hash_texto_normalizado": "fd776bbac6fc44eb1fb41812f5cdb4c938f8ddc76b3cddb71a5981d438d85aa0",
          "normalizacao": {
            "regras_aplicadas": [],
            "removido_total_chars": 0
          }
        }
      ],
      "filhos": [
        {
          "rotulo": "Parágrafo único",
          "tipo_dispositivo": "paragrafo",
          "caminho_estrutural": "art-7/par-1",
          "ordem": 1,
          "versoes": [
            {
              "vigencia_inicio": "21/12/2019",
              "vigencia_fim": null,
              "texto_normalizado": "Parágrafo único . Os recursos necessários à execução do disposto neste artigo são os caracterizados no inciso III do §1º do art. 43 da Lei federal nº 4.320, de 17 de março de 1964, provenientes de anulações parciais de dotações orçamentárias, de acordo com o quadro 2 desta portaria.",
              "hash_texto": "29a37bb5ff18a202cc9fa92301e698b04040708e6695057a627ba4170536eb0e",
              "status_vigencia": "vigente",
              "origem_alteracao": null,
              "texto_original_parser": "Parágrafo único . Os recursos necessários à execução do disposto\nneste artigo são os caracterizados no inciso III do §1º do art. 43\nda Lei federal nº 4.320, de 17 de março de 1964, provenientes de\nanulações parciais de dotações orçamentárias, de acordo com o\nquadro 2 desta portaria.",
              "hash_texto_normalizado": "01ffdeb3f2fec06b8d7a8acc9e29c99db4e372f088a6612586ff11edc8e8f70e",
              "normalizacao": {
                "regras_aplicadas": [],
                "removido_total_chars": 0
              }
            }
          ],
          "filhos": [],
          "ancoras": null
        }
      ],
      "ancoras": null
    },
    {
      "rotulo": "Art. 2º",
      "tipo_dispositivo": "artigo",
      "caminho_estrutural": "art-8",
      "ordem": 8,
      "versoes": [
        {
          "vigencia_inicio": "21/12/2019",
          "vigencia_fim": null,
          "texto_normalizado": "Art. 2º Esta Portaria entra em vigor nesta data. GABINETE DA SECRETÁRIA DE ESTADO DA ECONOMIA, em Goiânia, aos 26 dias do mês de Dezembro de 2019. CRISTIANE ALKMIN JUNQUEIRA SCHMIDT QUADRO 1 SUPLEMENTAÇÃO 2161 - AGÊNCIA GOIANA DE INFRAESTRUTURA E TRANSPORTES - GOINFRA CLASSIF. ORÇAMENTÁRIA DESCRIÇÃO DA AÇÃO GRUPO DE DESPESA FONTE MODALIDADE 15 451 1069",
          "hash_texto": "2032cdf357e4a14ecce1b40309acd803dc24f27924b6d6d3fc86b19cb45930b9",
          "status_vigencia": "vigente",
          "origem_alteracao": null,
          "texto_original_parser": "Art. 2º Esta Portaria entra em vigor nesta data.\nGABINETE DA SECRETÁRIA DE ESTADO DA ECONOMIA, em\nGoiânia, aos 26 dias do mês de Dezembro de 2019.\nCRISTIANE ALKMIN JUNQUEIRA SCHMIDT\nQUADRO 1\nSUPLEMENTAÇÃO\n2161 - AGÊNCIA GOIANA DE INFRAESTRUTURA E\nTRANSPORTES - GOINFRA\nCLASSIF.\nORÇAMENTÁRIA\nDESCRIÇÃO\nDA AÇÃO\nGRUPO DE\nDESPESA\nFONTE\nMODALIDADE\n15 451 1069",
          "hash_texto_normalizado": "e22ce207da19773401f4676e858854552b6b491dda125d840b143e6ade053bb3",
          "normalizacao": {
            "regras_aplicadas": [],
            "removido_total_chars": 0
          }
        }
      ],
      "filhos": [
        {
          "rotulo": "3",
          "tipo_dispositivo": "item",
          "caminho_estrutural": "art-8/item-1",
          "ordem": 1,
          "versoes": [
            {
              "vigencia_inicio": "21/12/2019",
              "vigencia_fim": null,
              "texto_normalizado": "3. 028 PAVIMENTAÇÃO DAS VIAS URBANAS 4 INVESTIMENTOS 100 90 SALDO CRÉD. SUPLEMENTAR VALOR DA DESPESA VALOR A SUPLEMENTAR R$ 236.559,29 R$",
              "hash_texto": "ba210a118c62107430c9a4464cbe7b98d265ad416fc7158c01e29b5335a9c123",
              "status_vigencia": "vigente",
              "origem_alteracao": null,
              "texto_original_parser": "3. 028\nPAVIMENTAÇÃO\nDAS VIAS\nURBANAS\n4 INVESTIMENTOS\n100\n90\nSALDO CRÉD.\nSUPLEMENTAR\nVALOR DA\nDESPESA\nVALOR A\nSUPLEMENTAR\nR$ 236.559,29\nR$",
              "hash_texto_normalizado": "c084c1d3713be597ced39c1fe010ab1436ae64c11b92b138b68b21293c011b5d",
              "normalizacao": {
                "regras_aplicadas": [],
                "removido_total_chars": 0
              }
            }
          ],
          "filhos": [],
          "ancoras": null
        },
        {
          "rotulo": "2",
          "tipo_dispositivo": "item",
          "caminho_estrutural": "art-8/item-2",
          "ordem": 2,
          "versoes": [
            {
              "vigencia_inicio": "21/12/2019",
              "vigencia_fim": null,
              "texto_normalizado": "2. 236.559,29 R$ 2.000.000,00 CLASSIF. ORÇAMENTÁRIA DESCRIÇÃO DA AÇÃO GRUPO DE DESPESA FONTE MODALIDADE 26 782 1068",
              "hash_texto": "85ef0f8568f44e8fedefaa1efc27b61856592cab64159a64413816f32d2db9c7",
              "status_vigencia": "vigente",
              "origem_alteracao": null,
              "texto_original_parser": "2. 236.559,29\nR$ 2.000.000,00\nCLASSIF.\nORÇAMENTÁRIA\nDESCRIÇÃO\nDA AÇÃO\nGRUPO DE\nDESPESA\nFONTE\nMODALIDADE\n26 782 1068",
              "hash_texto_normalizado": "8da6809898c18dddd48358291f152ac99d246bfbbbe19a7935d0ebeee29ac80b",
              "normalizacao": {
                "regras_aplicadas": [],
                "removido_total_chars": 0
              }
            }
          ],
          "filhos": [],
          "ancoras": null
        },
        {
          "rotulo": "3",
          "tipo_dispositivo": "item",
          "caminho_estrutural": "art-8/item-3",
          "ordem": 3,
          "versoes": [
            {
              "vigencia_inicio": "21/12/2019",
              "vigencia_fim": null,
              "texto_normalizado": "3. 029 CONSTRUÇÃO E PAVIMENTAÇÃO DE RODOVIAS ESTADUAIS 4 INVESTIMENTOS 100 90 SALDO CRÉD. SUPLEMENTAR VALOR DA DESPESA VALOR A SUPLEMENTAR R$ 56.499.741,57 R$",
              "hash_texto": "b4051471114e1bf03b730d924bec7b511c7ce9c7c121e482d00df5dab2eda63d",
              "status_vigencia": "vigente",
              "origem_alteracao": null,
              "texto_original_parser": "3. 029\nCONSTRUÇÃO\nE\nPAVIMENTAÇÃO\nDE RODOVIAS\nESTADUAIS\n4 INVESTIMENTOS\n100\n90\nSALDO CRÉD.\nSUPLEMENTAR\nVALOR DA\nDESPESA\nVALOR A\nSUPLEMENTAR\nR$ 56.499.741,57\nR$",
              "hash_texto_normalizado": "dc263f5634aa1b32222b0ff06e4142649552de2986956195ea083e8afa3b9881",
              "normalizacao": {
                "regras_aplicadas": [],
                "removido_total_chars": 0
              }
            }
          ],
          "filhos": [],
          "ancoras": null
        },
        {
          "rotulo": "61",
          "tipo_dispositivo": "item",
          "caminho_estrutural": "art-8/item-4",
          "ordem": 4,
          "versoes": [
            {
              "vigencia_inicio": "21/12/2019",
              "vigencia_fim": null,
              "texto_normalizado": "61. 209.933,13 R$ 4.710.191,56 CLASSIF. ORÇAMENTÁRIA DESCRIÇÃO DA AÇÃO GRUPO DE DESPESA FONTE MODALIDADE 26 782 1068",
              "hash_texto": "808f63568ba3484d877302d09592a906f61f972bbb2d15c1e5bb1dfd91a872b4",
              "status_vigencia": "vigente",
              "origem_alteracao": null,
              "texto_original_parser": "61. 209.933,13\nR$ 4.710.191,56\nCLASSIF.\nORÇAMENTÁRIA\nDESCRIÇÃO\nDA AÇÃO\nGRUPO DE\nDESPESA\nFONTE\nMODALIDADE\n26 782 1068",
              "hash_texto_normalizado": "61b411535e321e4fc6ed4d0686d2d6fa74ad1235c5a2924fe1b197ddd4528dca",
              "normalizacao": {
                "regras_aplicadas": [],
                "removido_total_chars": 0
              }
            }
          ],
          "filhos": [],
          "ancoras": null
        },
        {
          "rotulo": "3",
          "tipo_dispositivo": "item",
          "caminho_estrutural": "art-8/item-5",
          "ordem": 5,
          "versoes": [
            {
              "vigencia_inicio": "21/12/2019",
              "vigencia_fim": null,
              "texto_normalizado": "3. 030 CONSTRUÇÃO DE OBRAS DE ARTES ESPECIAIS 4 INVESTIMENTOS 100 90 SALDO CRÉD. SUPLEMENTAR VALOR DA DESPESA VALOR A SUPLEMENTAR R$ 13.931,05 R$",
              "hash_texto": "7a865f378c7d89a0221cc8ef448749f2135eeec62418c4d40287a4b255899da3",
              "status_vigencia": "vigente",
              "origem_alteracao": null,
              "texto_original_parser": "3. 030\nCONSTRUÇÃO\nDE OBRAS\nDE ARTES\nESPECIAIS\n4 INVESTIMENTOS\n100\n90\nSALDO CRÉD.\nSUPLEMENTAR\nVALOR DA\nDESPESA\nVALOR A\nSUPLEMENTAR\nR$ 13.931,05\nR$",
              "hash_texto_normalizado": "a2b36e750753a4fba88701b147b7ecc9c89cd1847dd5f9a6668c7c74289334ad",
              "normalizacao": {
                "regras_aplicadas": [],
                "removido_total_chars": 0
              }
            }
          ],
          "filhos": [],
          "ancoras": null
        },
        {
          "rotulo": "2",
          "tipo_dispositivo": "item",
          "caminho_estrutural": "art-8/item-6",
          "ordem": 6,
          "versoes": [
            {
              "vigencia_inicio": "21/12/2019",
              "vigencia_fim": null,
              "texto_normalizado": "2. 071.965,37 R$ 2.058.034,32 VALOR TOTAL A SUPLEMENTAR R$ 8.768.225,88 QUADRO 2 REDUÇÃO 1250 - FUNDO ESPECIAL DE COMUNICAÇÃO - FECOM CLASSIF. ORÇAMENTÁRIA DESCRIÇÃO DA AÇÃO GRUPO DE DESPESA FONTE MODALIDADE 04 131 1010",
              "hash_texto": "83f1ecd31672bf8f721a2a0e87ee693c13605bad9b2c9e8f8e7dec088ea75d22",
              "status_vigencia": "vigente",
              "origem_alteracao": null,
              "texto_original_parser": "2. 071.965,37\nR$ 2.058.034,32\nVALOR TOTAL A\nSUPLEMENTAR\nR$ 8.768.225,88\nQUADRO 2\nREDUÇÃO\n1250 - FUNDO ESPECIAL DE COMUNICAÇÃO - FECOM  \nCLASSIF.\nORÇAMENTÁRIA\nDESCRIÇÃO\nDA AÇÃO\nGRUPO DE\nDESPESA\nFONTE\nMODALIDADE\n04 131 1010",
              "hash_texto_normalizado": "ab020d10e24ae6e038c886dec6217c22541baeae6e144105b82274d92547bf82",
              "normalizacao": {
                "regras_aplicadas": [],
                "removido_total_chars": 0
              }
            }
          ],
          "filhos": [],
          "ancoras": null
        },
        {
          "rotulo": "2",
          "tipo_dispositivo": "item",
          "caminho_estrutural": "art-8/item-7",
          "ordem": 7,
          "versoes": [
            {
              "vigencia_inicio": "21/12/2019",
              "vigencia_fim": null,
              "texto_normalizado": "2. 038 DIVULGAÇÃO E VEICULAÇÃO DAS AÇÕES GOVERNAMENTAIS 3 - OUTRAS DESPESAS CORRENTES 100 90 SALDO A PROGRAMAR VALOR BLOQUEADO VALOR A REDUZIR R$ 0,00 R$",
              "hash_texto": "89ed01689a92937610f47f420499e483ce3e0d5ea07f3308639c5ff002e127af",
              "status_vigencia": "vigente",
              "origem_alteracao": null,
              "texto_original_parser": "2. 038\nDIVULGAÇÃO\nE VEICULAÇÃO\nDAS AÇÕES\nGOVERNAMENTAIS\n3 - OUTRAS\nDESPESAS\nCORRENTES\n100\n90\nSALDO A PROGRAMAR\nVALOR\nBLOQUEADO\nVALOR A REDUZIR\nR$ 0,00\nR$",
              "hash_texto_normalizado": "edfb2edb1720db2ef2bb91e3c9c68bbe55f789e2c31e7f75e6a698c783d88e95",
              "normalizacao": {
                "regras_aplicadas": [],
                "removido_total_chars": 0
              }
            }
          ],
          "filhos": [],
          "ancoras": null
        },
        {
          "rotulo": "8",
          "tipo_dispositivo": "item",
          "caminho_estrutural": "art-8/item-8",
          "ordem": 8,
          "versoes": [
            {
              "vigencia_inicio": "21/12/2019",
              "vigencia_fim": null,
              "texto_normalizado": "8. 768.225,88 R$ 8.768.225,88 VALOR TOTAL A REDUZIR R$ 8.768.225,88 <#ABC#163447#3#194584/> Protocolo 163447 DOE AMOR. DOE SANGUE. DIARIO OFICIAL DO ESTADO DE GOIAS Assinado digitalmente pela ABC - AGENCIA BRASIL CENTRAL CODIGO DE AUTENTICACAO: 21301716 4 Diário Oficial GOIÂNIA, SEGUNDA-FEIRA, 30 DE DEZEMBRO DE 2019 ANO 183 - DIÁRIO OFICIAL/GO N° 23.207 SUPLEMENTO EXTRA DIARIO OFICIAL DO ESTADO DE GOIAS Assinado digitalmente pela ABC - AGENCIA BRASIL CENTRAL CODIGO DE AUTENTICACAO: 21301716",
              "hash_texto": "3ec481fe7f14395d2aabdf03e8afb29f97f16051d614b54ac7c0f9a938a34496",
              "status_vigencia": "vigente",
              "origem_alteracao": null,
              "texto_original_parser": "8. 768.225,88\nR$ 8.768.225,88\nVALOR TOTAL A\nREDUZIR\nR$ 8.768.225,88\n<#ABC#163447#3#194584/>\nProtocolo 163447\nDOE AMOR. DOE SANGUE.\nDIARIO OFICIAL DO ESTADO DE GOIAS\nAssinado digitalmente pela ABC - AGENCIA BRASIL CENTRAL\nCODIGO DE AUTENTICACAO: 21301716\n4\nDiário Oficial\nGOIÂNIA, SEGUNDA-FEIRA, 30 DE DEZEMBRO DE 2019\nANO 183 - DIÁRIO OFICIAL/GO N° 23.207\nSUPLEMENTO EXTRA\nDIARIO OFICIAL DO ESTADO DE GOIAS\nAssinado digitalmente pela ABC - AGENCIA BRASIL CENTRAL\nCODIGO DE AUTENTICACAO: 21301716",
              "hash_texto_normalizado": "4d1d1c0d090802a62177eabf87bdc6c9a864fe927b0cabc078e082a392f807bf",
              "normalizacao": {
                "regras_aplicadas": [],
                "removido_total_chars": 0
              }
            }
          ],
          "filhos": [],
          "ancoras": null
        }
      ],
      "ancoras": null
    }
  ],
  "auditoria": {
    "run_id": "1f93f446-fe71-440c-9916-e6ccea010990",
    "parser_versao": "2.0",
    "gerado_em": "2025-10-14T00:27:24.415444Z"
  }
}